snehapre/__init__.py
snehapre/arithsample.py
snehapre/upperstring.py
snehapre-0.2.dist-info/LICENSE
snehapre-0.2.dist-info/METADATA
snehapre-0.2.dist-info/WHEEL
snehapre-0.2.dist-info/top_level.txt
snehapre-0.2.dist-info/RECORD
