Metadata-Version: 2.1
Name: snehapre
Version: 0.2
Summary: An example package
Home-page: UNKNOWN
Author: Sneha
Author-email: snehasgvs@gmail.com
License: MIT
Keywords: example,package
Platform: UNKNOWN
Classifier: License :: OSI Approved :: MIT License
Classifier: Programming Language :: Python :: 3
Classifier: Programming Language :: Python :: 3.9
Classifier: Programming Language :: Python :: 3.8
Classifier: Programming Language :: Python :: 3.7
Classifier: Programming Language :: Python :: 3.6
